[
    {
        "id": "25495194779",
        "type": "PushEvent",
        "actor": {
            "id": 1619443,
            "login": "phanrahan",
            "display_login": "phanrahan",
            "gravatar_id": "",
            "url": "https://api.github.com/users/phanrahan",
            "avatar_url": "https://avatars.githubusercontent.com/u/1619443?"
        },
        "repo": {
            "id": 344142973,
            "name": "phanrahan/agda",
            "url": "https://api.github.com/repos/phanrahan/agda"
        },
        "payload": {
            "push_id": 11799381116,
            "size": 1,
            "distinct_size": 1,
            "ref": "refs/heads/main",
            "head": "8873a40e4dc9261a089a449edd7c657c4980a4fe",
            "before": "665000fb1d99a3c9d87c742888ca6ce39c59e907",
            "commits": [
                {
                    "sha": "8873a40e4dc9261a089a449edd7c657c4980a4fe",
                    "author": {
                        "email": "hanrahan@cs.stanford.edu",
                        "name": "Pat Hanrahan"
                    },
                    "message": "Added polynomial types and literate agda example",
                    "distinct": true,
                    "url": "https://api.github.com/repos/phanrahan/agda/commits/8873a40e4dc9261a089a449edd7c657c4980a4fe"
                }
            ]
        },
        "public": true,
        "created_at": "2022-11-27T15:38:32Z"
    },
    {
        "id": "25495194779",
        "type": "PushEvent",
        "actor": {
            "id": 1619443,
            "login": "phanrahan",
            "display_login": "phanrahan",
            "gravatar_id": "",
            "url": "https://api.github.com/users/phanrahan",
            "avatar_url": "https://avatars.githubusercontent.com/u/1619443?"
        },
        "repo": {
            "id": 344142973,
            "name": "phanrahan/agda",
            "url": "https://api.github.com/repos/phanrahan/agda"
        },
        "payload": {
            "push_id": 11799381116,
            "size": 1,
            "distinct_size": 1,
            "ref": "refs/heads/main",
            "head": "8873a40e4dc9261a089a449edd7c657c4980a4fe",
            "before": "665000fb1d99a3c9d87c742888ca6ce39c59e907",
            "commits": [
                {
                    "sha": "8873a40e4dc9261a089a449edd7c657c4980a4fe",
                    "author": {
                        "email": "hanrahan@cs.stanford.edu",
                        "name": "Pat Hanrahan"
                    },
                    "message": "Added polynomial types and literate agda example",
                    "distinct": true,
                    "url": "https://api.github.com/repos/phanrahan/agda/commits/8873a40e4dc9261a089a449edd7c657c4980a4fe"
                }
            ]
        },
        "public": true,
        "created_at": "2022-11-27T15:38:32Z"
    },
    {
        "id": "25495194779",
        "type": "PushEvent",
        "actor": {
            "id": 1619443,
            "login": "phanrahan",
            "display_login": "phanrahan",
            "gravatar_id": "",
            "url": "https://api.github.com/users/phanrahan",
            "avatar_url": "https://avatars.githubusercontent.com/u/1619443?"
        },
        "repo": {
            "id": 344142973,
            "name": "phanrahan/agda",
            "url": "https://api.github.com/repos/phanrahan/agda"
        },
        "payload": {
            "push_id": 11799381116,
            "size": 1,
            "distinct_size": 1,
            "ref": "refs/heads/main",
            "head": "8873a40e4dc9261a089a449edd7c657c4980a4fe",
            "before": "665000fb1d99a3c9d87c742888ca6ce39c59e907",
            "commits": [
                {
                    "sha": "8873a40e4dc9261a089a449edd7c657c4980a4fe",
                    "author": {
                        "email": "hanrahan@cs.stanford.edu",
                        "name": "Pat Hanrahan"
                    },
                    "message": "Added polynomial types and literate agda example",
                    "distinct": true,
                    "url": "https://api.github.com/repos/phanrahan/agda/commits/8873a40e4dc9261a089a449edd7c657c4980a4fe"
                }
            ]
        },
        "public": true,
        "created_at": "2022-11-27T15:38:32Z"
    }
]