[
    {
        "id": "24205982535",
        "type": "IssuesEvent",
        "actor": {
            "id": 60022,
            "login": "thehappycoder",
            "display_login": "thehappycoder",
            "gravatar_id": "",
            "url": "https://api.github.com/users/thehappycoder",
            "avatar_url": "https://avatars.githubusercontent.com/u/60022?"
        },
        "repo": {
            "id": 72799153,
            "name": "rust-embedded/discovery",
            "url": "https://api.github.com/repos/rust-embedded/discovery"
        },
        "payload": {
            "action": "opened",
            "issue": {
                "url": "https://api.github.com/repos/rust-embedded/discovery/issues/468",
                "repository_url": "https://api.github.com/repos/rust-embedded/discovery",
                "labels_url": "https://api.github.com/repos/rust-embedded/discovery/issues/468/labels{/name}",
                "comments_url": "https://api.github.com/repos/rust-embedded/discovery/issues/468/comments",
                "events_url": "https://api.github.com/repos/rust-embedded/discovery/issues/468/events",
                "html_url": "https://github.com/rust-embedded/discovery/issues/468",
                "id": 1384941810,
                "node_id": "I_kwDOBFbTsc5SjIjy",
                "number": 468,
                "title": "Can't follow the book because gdb isn't available on Apple M1",
                "user": {
                    "login": "thehappycoder",
                    "id": 60022,
                    "node_id": "MDQ6VXNlcjYwMDIy",
                    "avatar_url": "https://avatars.githubusercontent.com/u/60022?v=4",
                    "gravatar_id": "",
                    "url": "https://api.github.com/users/thehappycoder",
                    "html_url": "https://github.com/thehappycoder",
                    "followers_url": "https://api.github.com/users/thehappycoder/followers",
                    "following_url": "https://api.github.com/users/thehappycoder/following{/other_user}",
                    "gists_url": "https://api.github.com/users/thehappycoder/gists{/gist_id}",
                    "starred_url": "https://api.github.com/users/thehappycoder/starred{/owner}{/repo}",
                    "subscriptions_url": "https://api.github.com/users/thehappycoder/subscriptions",
                    "organizations_url": "https://api.github.com/users/thehappycoder/orgs",
                    "repos_url": "https://api.github.com/users/thehappycoder/repos",
                    "events_url": "https://api.github.com/users/thehappycoder/events{/privacy}",
                    "received_events_url": "https://api.github.com/users/thehappycoder/received_events",
                    "type": "User",
                    "site_admin": false
                },
                "labels": [],
                "state": "open",
                "locked": false,
                "assignee": null,
                "assignees": [],
                "milestone": null,
                "comments": 0,
                "created_at": "2022-09-25T08:17:59Z",
                "updated_at": "2022-09-25T08:17:59Z",
                "closed_at": null,
                "author_association": "NONE",
                "active_lock_reason": null,
                "body": "This could be a good alternative https://github.com/knurling-rs/probe-run",
                "reactions": {
                    "url": "https://api.github.com/repos/rust-embedded/discovery/issues/468/reactions",
                    "total_count": 0,
                    "+1": 0,
                    "-1": 0,
                    "laugh": 0,
                    "hooray": 0,
                    "confused": 0,
                    "heart": 0,
                    "rocket": 0,
                    "eyes": 0
                },
                "timeline_url": "https://api.github.com/repos/rust-embedded/discovery/issues/468/timeline",
                "performed_via_github_app": null,
                "state_reason": null
            }
        },
        "public": true,
        "created_at": "2022-09-25T08:17:59Z",
        "org": {
            "id": 17707713,
            "login": "rust-embedded",
            "gravatar_id": "",
            "url": "https://api.github.com/orgs/rust-embedded",
            "avatar_url": "https://avatars.githubusercontent.com/u/17707713?"
        }
    },
    {
        "id": "24205982535",
        "type": "IssuesEvent",
        "actor": {
            "id": 60022,
            "login": "thehappycoder",
            "display_login": "thehappycoder",
            "gravatar_id": "",
            "url": "https://api.github.com/users/thehappycoder",
            "avatar_url": "https://avatars.githubusercontent.com/u/60022?"
        },
        "repo": {
            "id": 72799153,
            "name": "rust-embedded/discovery",
            "url": "https://api.github.com/repos/rust-embedded/discovery"
        },
        "payload": {
            "action": "opened",
            "issue": {
                "url": "https://api.github.com/repos/rust-embedded/discovery/issues/468",
                "repository_url": "https://api.github.com/repos/rust-embedded/discovery",
                "labels_url": "https://api.github.com/repos/rust-embedded/discovery/issues/468/labels{/name}",
                "comments_url": "https://api.github.com/repos/rust-embedded/discovery/issues/468/comments",
                "events_url": "https://api.github.com/repos/rust-embedded/discovery/issues/468/events",
                "html_url": "https://github.com/rust-embedded/discovery/issues/468",
                "id": 1384941810,
                "node_id": "I_kwDOBFbTsc5SjIjy",
                "number": 468,
                "title": "Can't follow the book because gdb isn't available on Apple M1",
                "user": {
                    "login": "thehappycoder",
                    "id": 60022,
                    "node_id": "MDQ6VXNlcjYwMDIy",
                    "avatar_url": "https://avatars.githubusercontent.com/u/60022?v=4",
                    "gravatar_id": "",
                    "url": "https://api.github.com/users/thehappycoder",
                    "html_url": "https://github.com/thehappycoder",
                    "followers_url": "https://api.github.com/users/thehappycoder/followers",
                    "following_url": "https://api.github.com/users/thehappycoder/following{/other_user}",
                    "gists_url": "https://api.github.com/users/thehappycoder/gists{/gist_id}",
                    "starred_url": "https://api.github.com/users/thehappycoder/starred{/owner}{/repo}",
                    "subscriptions_url": "https://api.github.com/users/thehappycoder/subscriptions",
                    "organizations_url": "https://api.github.com/users/thehappycoder/orgs",
                    "repos_url": "https://api.github.com/users/thehappycoder/repos",
                    "events_url": "https://api.github.com/users/thehappycoder/events{/privacy}",
                    "received_events_url": "https://api.github.com/users/thehappycoder/received_events",
                    "type": "User",
                    "site_admin": false
                },
                "labels": [],
                "state": "open",
                "locked": false,
                "assignee": null,
                "assignees": [],
                "milestone": null,
                "comments": 0,
                "created_at": "2022-09-25T08:17:59Z",
                "updated_at": "2022-09-25T08:17:59Z",
                "closed_at": null,
                "author_association": "NONE",
                "active_lock_reason": null,
                "body": "This could be a good alternative https://github.com/knurling-rs/probe-run",
                "reactions": {
                    "url": "https://api.github.com/repos/rust-embedded/discovery/issues/468/reactions",
                    "total_count": 0,
                    "+1": 0,
                    "-1": 0,
                    "laugh": 0,
                    "hooray": 0,
                    "confused": 0,
                    "heart": 0,
                    "rocket": 0,
                    "eyes": 0
                },
                "timeline_url": "https://api.github.com/repos/rust-embedded/discovery/issues/468/timeline",
                "performed_via_github_app": null,
                "state_reason": null
            }
        },
        "public": true,
        "created_at": "2022-09-25T08:17:59Z",
        "org": {
            "id": 17707713,
            "login": "rust-embedded",
            "gravatar_id": "",
            "url": "https://api.github.com/orgs/rust-embedded",
            "avatar_url": "https://avatars.githubusercontent.com/u/17707713?"
        }
    },
    {
        "id": "24205982535",
        "type": "IssuesEvent",
        "actor": {
            "id": 60022,
            "login": "thehappycoder",
            "display_login": "thehappycoder",
            "gravatar_id": "",
            "url": "https://api.github.com/users/thehappycoder",
            "avatar_url": "https://avatars.githubusercontent.com/u/60022?"
        },
        "repo": {
            "id": 72799153,
            "name": "rust-embedded/discovery",
            "url": "https://api.github.com/repos/rust-embedded/discovery"
        },
        "payload": {
            "action": "opened",
            "issue": {
                "url": "https://api.github.com/repos/rust-embedded/discovery/issues/468",
                "repository_url": "https://api.github.com/repos/rust-embedded/discovery",
                "labels_url": "https://api.github.com/repos/rust-embedded/discovery/issues/468/labels{/name}",
                "comments_url": "https://api.github.com/repos/rust-embedded/discovery/issues/468/comments",
                "events_url": "https://api.github.com/repos/rust-embedded/discovery/issues/468/events",
                "html_url": "https://github.com/rust-embedded/discovery/issues/468",
                "id": 1384941810,
                "node_id": "I_kwDOBFbTsc5SjIjy",
                "number": 468,
                "title": "Can't follow the book because gdb isn't available on Apple M1",
                "user": {
                    "login": "thehappycoder",
                    "id": 60022,
                    "node_id": "MDQ6VXNlcjYwMDIy",
                    "avatar_url": "https://avatars.githubusercontent.com/u/60022?v=4",
                    "gravatar_id": "",
                    "url": "https://api.github.com/users/thehappycoder",
                    "html_url": "https://github.com/thehappycoder",
                    "followers_url": "https://api.github.com/users/thehappycoder/followers",
                    "following_url": "https://api.github.com/users/thehappycoder/following{/other_user}",
                    "gists_url": "https://api.github.com/users/thehappycoder/gists{/gist_id}",
                    "starred_url": "https://api.github.com/users/thehappycoder/starred{/owner}{/repo}",
                    "subscriptions_url": "https://api.github.com/users/thehappycoder/subscriptions",
                    "organizations_url": "https://api.github.com/users/thehappycoder/orgs",
                    "repos_url": "https://api.github.com/users/thehappycoder/repos",
                    "events_url": "https://api.github.com/users/thehappycoder/events{/privacy}",
                    "received_events_url": "https://api.github.com/users/thehappycoder/received_events",
                    "type": "User",
                    "site_admin": false
                },
                "labels": [],
                "state": "open",
                "locked": false,
                "assignee": null,
                "assignees": [],
                "milestone": null,
                "comments": 0,
                "created_at": "2022-09-25T08:17:59Z",
                "updated_at": "2022-09-25T08:17:59Z",
                "closed_at": null,
                "author_association": "NONE",
                "active_lock_reason": null,
                "body": "This could be a good alternative https://github.com/knurling-rs/probe-run",
                "reactions": {
                    "url": "https://api.github.com/repos/rust-embedded/discovery/issues/468/reactions",
                    "total_count": 0,
                    "+1": 0,
                    "-1": 0,
                    "laugh": 0,
                    "hooray": 0,
                    "confused": 0,
                    "heart": 0,
                    "rocket": 0,
                    "eyes": 0
                },
                "timeline_url": "https://api.github.com/repos/rust-embedded/discovery/issues/468/timeline",
                "performed_via_github_app": null,
                "state_reason": null
            }
        },
        "public": true,
        "created_at": "2022-09-25T08:17:59Z",
        "org": {
            "id": 17707713,
            "login": "rust-embedded",
            "gravatar_id": "",
            "url": "https://api.github.com/orgs/rust-embedded",
            "avatar_url": "https://avatars.githubusercontent.com/u/17707713?"
        }
    }
]